odoo/addons/sale_payment_sheet_financial_risk/README.rst
odoo/addons/sale_payment_sheet_financial_risk/__init__.py
odoo/addons/sale_payment_sheet_financial_risk/__manifest__.py
odoo/addons/sale_payment_sheet_financial_risk/i18n/es.po
odoo/addons/sale_payment_sheet_financial_risk/i18n/sale_payment_sheet_financial_risk.pot
odoo/addons/sale_payment_sheet_financial_risk/models/__init__.py
odoo/addons/sale_payment_sheet_financial_risk/models/res_partner.py
odoo/addons/sale_payment_sheet_financial_risk/readme/CONTRIBUTORS.rst
odoo/addons/sale_payment_sheet_financial_risk/readme/DESCRIPTION.rst
odoo/addons/sale_payment_sheet_financial_risk/readme/USAGE.rst
odoo/addons/sale_payment_sheet_financial_risk/static/description/deduct_sale_payment_sheet_set.png
odoo/addons/sale_payment_sheet_financial_risk/static/description/deduct_sale_payment_sheet_unset.png
odoo/addons/sale_payment_sheet_financial_risk/static/description/icon.png
odoo/addons/sale_payment_sheet_financial_risk/static/description/index.html
odoo/addons/sale_payment_sheet_financial_risk/tests/__init__.py
odoo/addons/sale_payment_sheet_financial_risk/tests/test_sale_payment_sheet_financial_risk.py
odoo/addons/sale_payment_sheet_financial_risk/views/res_partner_view.xml
odoo/addons/sale_payment_sheet_financial_risk/views/sale_payment_sheet_financial_risk_view.xml
odoo13_addon_sale_payment_sheet_financial_risk-13.0.1.1.0.dist-info/METADATA
odoo13_addon_sale_payment_sheet_financial_risk-13.0.1.1.0.dist-info/WHEEL
odoo13_addon_sale_payment_sheet_financial_risk-13.0.1.1.0.dist-info/top_level.txt
odoo13_addon_sale_payment_sheet_financial_risk-13.0.1.1.0.dist-info/RECORD
